oblv_client-0.1.15.dist-info/METADATA
oblv_client-0.1.15.dist-info/WHEEL
oblv_client/__init__.py
oblv_client/oblv_client.cpython-312-darwin.so
oblv_client-0.1.15.dist-info/RECORD
