Metadata-Version: 2.1
Name: oblv-client
Version: 0.1.15
Classifier: Programming Language :: Rust
Classifier: Programming Language :: Python :: Implementation :: CPython
Classifier: Programming Language :: Python :: Implementation :: PyPy
Requires-Dist: urllib3
Summary: python bindings for using enclaves with oblivious tooling
Home-Page: https://oblivious.ai
Author: OBLV Devs <hello@oblivious.ai>
Author-email: OBLV Devs <hello@oblivious.ai>
License: Apache-2.0
Requires-Python: >=3.7
